[
  {
    "IconUrl": "https://raw.githubusercontent.com/thakyZ/MyDalamudPlugins/main/plugins/EmoteCmdComplex/images/icon.png",
    "LoadPriority": 0,
    "Author": "Neko Boi Nick",
    "LastUpdated": 1698627024,
    "RepoUrl": "https://github.com/thakyZ/EmoteCmdComplex-dalamud",
    "LoadSync": false,
    "ApplicableVersion": "any",
    "DownloadLinkUpdate": "https://raw.githubusercontent.com/thakyZ/MyDalamudPlugins/main/plugins/EmoteCmdComplex/latest.zip",
    "Description": "This plugin adds a command so that you can have more complex custom emotes.\nSuch as if you want to have one macro do an emote on a targeting and non-targeting basis.",
    "InternalName": "EmoteCmdComplex",
    "AssemblyVersion": "1.0.2.8",
    "IsHide": false,
    "CanUnloadAsync": false,
    "LoadRequiredState": 0,
    "Name": "Emote Command Complex",
    "AcceptsFeedback": false,
    "DownloadCount": 6416,
    "IsTestingExclusive": false,
    "Punchline": "Complex custom emotes now with targets!",
    "Tags": [
      "Social"
    ],
    "DownloadLinkTesting": "https://raw.githubusercontent.com/thakyZ/MyDalamudPlugins/main/plugins/EmoteCmdComplex/latest.zip",
    "DalamudApiLevel": 9,
    "Changelog": "Fixed unreadable memory.",
    "DownloadLinkInstall": "https://raw.githubusercontent.com/thakyZ/MyDalamudPlugins/main/plugins/EmoteCmdComplex/latest.zip"
  },
  {
    "IconUrl": "https://raw.githubusercontent.com/thakyZ/MyDalamudPlugins/main/plugins/ResetEnmityCommand/images/icon.png",
    "LoadPriority": 0,
    "Author": "akira0245",
    "LastUpdated": 1720898692,
    "RepoUrl": "https://github.com/thakyZ/Dalamud-ResetEnmityCommand",
    "LoadSync": false,
    "ApplicableVersion": "any",
    "DownloadLinkUpdate": "https://raw.githubusercontent.com/thakyZ/MyDalamudPlugins/main/plugins/ResetEnmityCommand/latest.zip",
    "Description": "Add a reset striking dummy enmity command.",
    "InternalName": "ResetEnmityCommand",
    "AssemblyVersion": "0.0.1.9",
    "IsHide": false,
    "CanUnloadAsync": false,
    "LoadRequiredState": 0,
    "Name": "Reset Enmity Command",
    "AcceptsFeedback": false,
    "DownloadCount": 330,
    "IsTestingExclusive": false,
    "Punchline": "Add a reset striking dummy enmity command.",
    "Tags": [
      "akira",
      "striking",
      "battle",
      "train"
    ],
    "DownloadLinkTesting": "https://raw.githubusercontent.com/thakyZ/MyDalamudPlugins/main/plugins/ResetEnmityCommand/latest.zip",
    "DalamudApiLevel": 11,
    "Changelog": "Fixed Stack Overflow",
    "DownloadLinkInstall": "https://raw.githubusercontent.com/thakyZ/MyDalamudPlugins/main/plugins/ResetEnmityCommand/latest.zip"
  },
  {
    "IconUrl": "https://raw.githubusercontent.com/thakyZ/MyDalamudPlugins/main/plugins/HousingTimeoutReminder/images/icon.png",
    "LoadPriority": 0,
    "Author": "Neko Boi Nick",
    "LastUpdated": 1729381287,
    "RepoUrl": "https://github.com/thakyZ/HousingTimeoutReminder",
    "LoadSync": false,
    "ApplicableVersion": "any",
    "DownloadLinkUpdate": "https://raw.githubusercontent.com/thakyZ/MyDalamudPlugins/main/plugins/HousingTimeoutReminder/latest.zip",
    "Description": "A plugin to remind you about your house on FFXIV just in case you forgot to visit it.",
    "InternalName": "HousingTimeoutReminder",
    "AssemblyVersion": "1.0.3.1",
    "IsHide": false,
    "CanUnloadAsync": false,
    "LoadRequiredState": 0,
    "Name": "Housing Timeout Reminder",
    "AcceptsFeedback": false,
    "DownloadCount": 91,
    "IsTestingExclusive": false,
    "Punchline": "Remind you to visit your house just in case you forgot.",
    "Tags": [
      "Utility"
    ],
    "DownloadLinkTesting": "https://raw.githubusercontent.com/thakyZ/MyDalamudPlugins/main/plugins/HousingTimeoutReminder/latest.zip",
    "DalamudApiLevel": 11,
    "Changelog": "Update to ApiX and DawnTrail",
    "DownloadLinkInstall": "https://raw.githubusercontent.com/thakyZ/MyDalamudPlugins/main/plugins/HousingTimeoutReminder/latest.zip"
  },
  {
    "IconUrl": "https://raw.githubusercontent.com/thakyZ/MyDalamudPlugins/main/plugins/BetterMinionRoulette/images/icon.png",
    "LoadPriority": 0,
    "Author": "Neko Boi Nick",
    "LastUpdated": 1693235973,
    "RepoUrl": "https://github.com/thakyZ/BetterMinionRoulette",
    "LoadSync": false,
    "ApplicableVersion": "any",
    "DownloadLinkUpdate": "https://raw.githubusercontent.com/thakyZ/MyDalamudPlugins/main/plugins/BetterMinionRoulette/latest.zip",
    "Description": "Allows any number of minions to be enabled for the minion roulette, instead of having to choose between the\n\"up to 30\" and \"EVERYTHING\" modes supported by the game. Also has (or will have) an option to omit the\nisland sanctuary minions from being spawned.",
    "InternalName": "BetterMinionRoulette",
    "AssemblyVersion": "1.0.0.6",
    "IsHide": false,
    "CanUnloadAsync": false,
    "LoadRequiredState": 0,
    "Name": "Better Minion Roulette",
    "AcceptsFeedback": false,
    "DownloadCount": 6509,
    "IsTestingExclusive": false,
    "Punchline": "Choose which minions show up in the minions roulette.",
    "Tags": [
      "Minion",
      "Utility"
    ],
    "DownloadLinkTesting": "https://raw.githubusercontent.com/thakyZ/MyDalamudPlugins/main/plugins/BetterMinionRoulette/latest.zip",
    "DalamudApiLevel": 11,
    "Changelog": "Updated to Dalamud API 9",
    "DownloadLinkInstall": "https://raw.githubusercontent.com/thakyZ/MyDalamudPlugins/main/plugins/BetterMinionRoulette/latest.zip"
  }
]
