[
  {
    "ApplicableVersion": "any",
    "Changelog": "Fixed unreadable memory.",
    "RepoUrl": "https://github.com/thakyZ/EmoteCmdComplex-dalamud",
    "InternalName": "EmoteCmdComplex",
    "Author": "Neko Boi Nick",
    "IconUrl": "https://raw.githubusercontent.com/thakyZ/MyDalamudPlugins/main/plugins/EmoteCmdComplex/images/icon.png",
    "Description": "This plugin adds a command so that you can have more complex custom emotes.\nSuch as if you want to have one macro do an emote on a targeting and non-targeting basis.",
    "Name": "Emote Command Complex",
    "Tags": [
      "Social"
    ],
    "DalamudApiLevel": 9,
    "Punchline": "Complex custom emotes now with targets!",
    "IsHide": false,
    "IsTestingExclusive": false,
    "AssemblyVersion": "1.0.2.8",
    "LastUpdated": 1698627024,
    "DownloadCount": 2186,
    "DownloadLinkInstall": "https://raw.githubusercontent.com/thakyZ/MyDalamudPlugins/main/plugins/EmoteCmdComplex/latest.zip",
    "DownloadLinkTesting": "https://raw.githubusercontent.com/thakyZ/MyDalamudPlugins/main/plugins/EmoteCmdComplex/latest.zip",
    "DownloadLinkUpdate": "https://raw.githubusercontent.com/thakyZ/MyDalamudPlugins/main/plugins/EmoteCmdComplex/latest.zip"
  },
  {
    "Changelog": "Fixed Stack Overflow",
    "Repourl": "https://github.com/thakyZ/Dalamud-ResetEnmityCommand",
    "Internalname": "ResetEnmityCommand",
    "Author": "akira0245",
    "Tags": [
      "akira",
      "striking",
      "battle",
      "train"
    ],
    "Description": "Add a reset striking dummy enmity command.",
    "Name": "Reset Enmity Command",
    "Iconurl": "https://raw.githubusercontent.com/thakyZ/MyDalamudPlugins/main/plugins/ResetEnmityCommand/images/icon.png",
    "Punchline": "Add a reset striking dummy enmity command.",
    "Dalamudapiversion": 9,
    "DalamudApiLevel": 9,
    "IsHide": false,
    "IsTestingExclusive": false,
    "AssemblyVersion": "0.0.1.8",
    "LastUpdated": 1698631462,
    "DownloadCount": 2159,
    "DownloadLinkInstall": "https://raw.githubusercontent.com/thakyZ/MyDalamudPlugins/main/plugins/ResetEnmityCommand/latest.zip",
    "DownloadLinkTesting": "https://raw.githubusercontent.com/thakyZ/MyDalamudPlugins/main/plugins/ResetEnmityCommand/latest.zip",
    "DownloadLinkUpdate": "https://raw.githubusercontent.com/thakyZ/MyDalamudPlugins/main/plugins/ResetEnmityCommand/latest.zip"
  },
  {
    "ApplicableVersion": "any",
    "Changelog": "Fixed uncaught exception when saving.",
    "RepoUrl": "https://github.com/thakyZ/HousingTimeoutReminder",
    "InternalName": "HousingTimeoutReminder",
    "Author": "Neko Boi Nick",
    "IconUrl": "https://raw.githubusercontent.com/thakyZ/MyDalamudPlugins/main/plugins/HousingTimeoutReminder/images/icon.png",
    "Description": "A plugin to remind you about your house on FFXIV just in case you forgot to visit it.",
    "Name": "Housing Timeout Reminder",
    "Tags": [
      "Utility"
    ],
    "DalamudApiLevel": 9,
    "Punchline": "Remind you to visit your house just in case you forgot.",
    "IsHide": false,
    "IsTestingExclusive": false,
    "AssemblyVersion": "1.0.2.4",
    "LastUpdated": 1703601597,
    "DownloadCount": 1004,
    "DownloadLinkInstall": "https://raw.githubusercontent.com/thakyZ/MyDalamudPlugins/main/plugins/HousingTimeoutReminder/latest.zip",
    "DownloadLinkTesting": "https://raw.githubusercontent.com/thakyZ/MyDalamudPlugins/main/plugins/HousingTimeoutReminder/latest.zip",
    "DownloadLinkUpdate": "https://raw.githubusercontent.com/thakyZ/MyDalamudPlugins/main/plugins/HousingTimeoutReminder/latest.zip"
  },
  {
    "ApplicableVersion": "any",
    "Changelog": "Updated to Dalamud 7.6.3.0",
    "RepoUrl": "https://github.com/thakyZ/BetterMinionRoulette-Dalamud",
    "InternalName": "BetterMinionRoulette",
    "Author": "Neko Boi Nick",
    "IconUrl": "https://raw.githubusercontent.com/thakyZ/MyDalamudPlugins/main/plugins/BetterMinionRoulette/images/icon.png",
    "Description": "Allows any number of minions to be enabled for the minion roulette, instead of having to choose between the\n\"up to 30\" and \"EVERYTHING\" modes supported by the game. Also has (or will have) an option to omit the\nisland sanctuary minions from being spawned.",
    "Name": "Better Minion Roulette",
    "Tags": [
      "Minion",
      "Utility"
    ],
    "DalamudApiLevel": 8,
    "Punchline": "Choose which minions show up in the minions roulette.",
    "IsHide": false,
    "IsTestingExclusive": false,
    "AssemblyVersion": "1.0.0.6",
    "LastUpdated": 1693235973,
    "DownloadCount": 2263,
    "DownloadLinkInstall": "https://raw.githubusercontent.com/thakyZ/MyDalamudPlugins/main/plugins/BetterMinionRoulette/latest.zip",
    "DownloadLinkTesting": "https://raw.githubusercontent.com/thakyZ/MyDalamudPlugins/main/plugins/BetterMinionRoulette/latest.zip",
    "DownloadLinkUpdate": "https://raw.githubusercontent.com/thakyZ/MyDalamudPlugins/main/plugins/BetterMinionRoulette/latest.zip"
  }
]
