[
  {
    "Author": "Neko Boi Nick",
    "IconUrl": "https://raw.githubusercontent.com/thakyZ/MyDalamudPlugins/main/plugins/EmoteCmdComplex/images/icon.png",
    "ApplicableVersion": "any",
    "Tags": [
      "Social"
    ],
    "RepoUrl": "https://github.com/thakyZ/EmoteCmdComplex-dalamud",
    "InternalName": "EmoteCmdComplex",
    "DalamudApiLevel": 9,
    "Changelog": "Fixed unreadable memory.",
    "Name": "Emote Command Complex",
    "Punchline": "Complex custom emotes now with targets!",
    "Description": "This plugin adds a command so that you can have more complex custom emotes.\nSuch as if you want to have one macro do an emote on a targeting and non-targeting basis.",
    "IsHide": false,
    "IsTestingExclusive": false,
    "AssemblyVersion": "1.0.2.8",
    "LastUpdated": 1698627024,
    "DownloadCount": 1626,
    "DownloadLinkInstall": "https://raw.githubusercontent.com/thakyZ/MyDalamudPlugins/main/plugins/EmoteCmdComplex/latest.zip",
    "DownloadLinkTesting": "https://raw.githubusercontent.com/thakyZ/MyDalamudPlugins/main/plugins/EmoteCmdComplex/latest.zip",
    "DownloadLinkUpdate": "https://raw.githubusercontent.com/thakyZ/MyDalamudPlugins/main/plugins/EmoteCmdComplex/latest.zip"
  },
  {
    "Author": "akira0245",
    "Iconurl": "https://raw.githubusercontent.com/thakyZ/MyDalamudPlugins/main/plugins/ResetEnmityCommand/images/icon.png",
    "Tags": [
      "akira",
      "striking",
      "battle",
      "train"
    ],
    "Internalname": "ResetEnmityCommand",
    "Changelog": "Fixed Stack Overflow",
    "Name": "Reset Enmity Command",
    "Punchline": "Add a reset striking dummy enmity command.",
    "Dalamudapiversion": 9,
    "Repourl": "https://github.com/thakyZ/Dalamud-ResetEnmityCommand",
    "Description": "Add a reset striking dummy enmity command.",
    "DalamudApiLevel": 9,
    "IsHide": false,
    "IsTestingExclusive": false,
    "AssemblyVersion": "0.0.1.8",
    "LastUpdated": 1698631462,
    "DownloadCount": 1606,
    "DownloadLinkInstall": "https://raw.githubusercontent.com/thakyZ/MyDalamudPlugins/main/plugins/ResetEnmityCommand/latest.zip",
    "DownloadLinkTesting": "https://raw.githubusercontent.com/thakyZ/MyDalamudPlugins/main/plugins/ResetEnmityCommand/latest.zip",
    "DownloadLinkUpdate": "https://raw.githubusercontent.com/thakyZ/MyDalamudPlugins/main/plugins/ResetEnmityCommand/latest.zip"
  },
  {
    "Author": "Neko Boi Nick",
    "IconUrl": "https://raw.githubusercontent.com/thakyZ/MyDalamudPlugins/main/plugins/HousingTimeoutReminder/images/icon.png",
    "ApplicableVersion": "any",
    "Tags": [
      "Utility"
    ],
    "RepoUrl": "https://github.com/thakyZ/HousingTimeoutReminder",
    "InternalName": "HousingTimeoutReminder",
    "DalamudApiLevel": 9,
    "Changelog": "Fixed uncaught exception when saving.",
    "Name": "Housing Timeout Reminder",
    "Punchline": "Remind you to visit your house just in case you forgot.",
    "Description": "A plugin to remind you about your house on FFXIV just in case you forgot to visit it.",
    "IsHide": false,
    "IsTestingExclusive": false,
    "AssemblyVersion": "1.0.2.4",
    "LastUpdated": 1703601597,
    "DownloadCount": 454,
    "DownloadLinkInstall": "https://raw.githubusercontent.com/thakyZ/MyDalamudPlugins/main/plugins/HousingTimeoutReminder/latest.zip",
    "DownloadLinkTesting": "https://raw.githubusercontent.com/thakyZ/MyDalamudPlugins/main/plugins/HousingTimeoutReminder/latest.zip",
    "DownloadLinkUpdate": "https://raw.githubusercontent.com/thakyZ/MyDalamudPlugins/main/plugins/HousingTimeoutReminder/latest.zip"
  },
  {
    "Author": "Neko Boi Nick",
    "IconUrl": "https://raw.githubusercontent.com/thakyZ/MyDalamudPlugins/main/plugins/BetterMinionRoulette/images/icon.png",
    "ApplicableVersion": "any",
    "Tags": [
      "Minion",
      "Utility"
    ],
    "RepoUrl": "https://github.com/thakyZ/BetterMinionRoulette-Dalamud",
    "InternalName": "BetterMinionRoulette",
    "DalamudApiLevel": 8,
    "Changelog": "Updated to Dalamud 7.6.3.0",
    "Name": "Better Minion Roulette",
    "Punchline": "Choose which minions show up in the minions roulette.",
    "Description": "Allows any number of minions to be enabled for the minion roulette, instead of having to choose between the\n\"up to 30\" and \"EVERYTHING\" modes supported by the game. Also has (or will have) an option to omit the\nisland sanctuary minions from being spawned.",
    "IsHide": false,
    "IsTestingExclusive": false,
    "AssemblyVersion": "1.0.0.6",
    "LastUpdated": 1693235973,
    "DownloadCount": 1705,
    "DownloadLinkInstall": "https://raw.githubusercontent.com/thakyZ/MyDalamudPlugins/main/plugins/BetterMinionRoulette/latest.zip",
    "DownloadLinkTesting": "https://raw.githubusercontent.com/thakyZ/MyDalamudPlugins/main/plugins/BetterMinionRoulette/latest.zip",
    "DownloadLinkUpdate": "https://raw.githubusercontent.com/thakyZ/MyDalamudPlugins/main/plugins/BetterMinionRoulette/latest.zip"
  }
]
